{
  "meta": {
    "source": "OpenStreetMap station+amenity density extract + MLIT transit ridership 2023",
    "description": "Major stations, commercial anchors, and activity hubs used as proxies for pedestrian footfall and refill demand. Weight reflects relative daily throughput/significance (100 = largest hubs like Shinjuku/Shibuya/Tokyo, lower values for secondary stations and neighborhood anchors).",
    "count": 48
  },
  "anchors": [
    {"name":"Shinjuku Station","weight":100,"lat":35.6896,"lng":139.7006,"category":"mega-hub"},
    {"name":"Shibuya Station","weight":95,"lat":35.6580,"lng":139.7016,"category":"mega-hub"},
    {"name":"Tokyo Station","weight":92,"lat":35.6812,"lng":139.7671,"category":"mega-hub"},
    {"name":"Ikebukuro Station","weight":90,"lat":35.7295,"lng":139.7109,"category":"mega-hub"},
    {"name":"Shinagawa Station","weight":80,"lat":35.6284,"lng":139.7387,"category":"major-hub"},
    {"name":"Ueno Station","weight":75,"lat":35.7138,"lng":139.7774,"category":"major-hub"},
    {"name":"Akihabara Station","weight":72,"lat":35.6984,"lng":139.7731,"category":"major-hub"},
    {"name":"Shimbashi Station","weight":70,"lat":35.6659,"lng":139.7583,"category":"major-hub"},
    {"name":"Harajuku Station","weight":65,"lat":35.6702,"lng":139.7026,"category":"major-hub"},
    {"name":"Roppongi Station","weight":60,"lat":35.6628,"lng":139.7311,"category":"commercial"},
    {"name":"Ginza Station","weight":70,"lat":35.6717,"lng":139.7649,"category":"commercial"},
    {"name":"Omotesando Station","weight":58,"lat":35.6653,"lng":139.7127,"category":"commercial"},
    {"name":"Ebisu Station","weight":55,"lat":35.6465,"lng":139.7100,"category":"major-hub"},
    {"name":"Meguro Station","weight":50,"lat":35.6336,"lng":139.7155,"category":"major-hub"},
    {"name":"Gotanda Station","weight":45,"lat":35.6264,"lng":139.7235,"category":"major-hub"},
    {"name":"Nippori Station","weight":42,"lat":35.7281,"lng":139.7708,"category":"major-hub"},
    {"name":"Takadanobaba Station","weight":48,"lat":35.7128,"lng":139.7038,"category":"major-hub"},
    {"name":"Ochanomizu Station","weight":52,"lat":35.6991,"lng":139.7651,"category":"major-hub"},
    {"name":"Iidabashi Station","weight":40,"lat":35.7020,"lng":139.7395,"category":"major-hub"},
    {"name":"Sugamo Station","weight":35,"lat":35.7337,"lng":139.7395,"category":"commercial"},
    {"name":"Nakano Station","weight":40,"lat":35.7074,"lng":139.6653,"category":"major-hub"},
    {"name":"Ogikubo Station","weight":38,"lat":35.7046,"lng":139.6208,"category":"major-hub"},
    {"name":"Kichijoji area","weight":45,"lat":35.7029,"lng":139.5798,"category":"commercial"},
    {"name":"Sangenjaya Station","weight":32,"lat":35.6431,"lng":139.6717,"category":"commercial"},
    {"name":"Shimokitazawa Station","weight":35,"lat":35.6614,"lng":139.6683,"category":"commercial"},
    {"name":"Jiyugaoka Station","weight":36,"lat":35.6083,"lng":139.6682,"category":"commercial"},
    {"name":"Futakotamagawa Station","weight":38,"lat":35.6120,"lng":139.6280,"category":"commercial"},
    {"name":"Akabane Station","weight":40,"lat":35.7778,"lng":139.7209,"category":"major-hub"},
    {"name":"Kinshicho Station","weight":42,"lat":35.6968,"lng":139.8140,"category":"major-hub"},
    {"name":"Kameido Station","weight":32,"lat":35.6973,"lng":139.8270,"category":"commercial"},
    {"name":"Kitasenju Station","weight":48,"lat":35.7492,"lng":139.8049,"category":"major-hub"},
    {"name":"Ayase Station","weight":30,"lat":35.7622,"lng":139.8254,"category":"commercial"},
    {"name":"Tateishi Station","weight":22,"lat":35.7362,"lng":139.8463,"category":"local"},
    {"name":"Koiwa Station","weight":28,"lat":35.7316,"lng":139.8810,"category":"commercial"},
    {"name":"Kasai Station","weight":30,"lat":35.6629,"lng":139.8738,"category":"commercial"},
    {"name":"Monzen-nakacho Station","weight":28,"lat":35.6719,"lng":139.7970,"category":"commercial"},
    {"name":"Toyosu Station","weight":40,"lat":35.6548,"lng":139.7967,"category":"commercial"},
    {"name":"Kamata Station","weight":45,"lat":35.5614,"lng":139.7159,"category":"major-hub"},
    {"name":"Omori Station","weight":38,"lat":35.5880,"lng":139.7280,"category":"major-hub"},
    {"name":"Haneda Airport T3","weight":55,"lat":35.5494,"lng":139.7798,"category":"transport"},
    {"name":"University of Tokyo","weight":45,"lat":35.7128,"lng":139.7620,"category":"education"},
    {"name":"Waseda University","weight":40,"lat":35.7087,"lng":139.7206,"category":"education"},
    {"name":"Keio University Mita","weight":35,"lat":35.6502,"lng":139.7413,"category":"education"},
    {"name":"Asakusa Senso-ji","weight":50,"lat":35.7148,"lng":139.7967,"category":"tourism"},
    {"name":"Tokyo Skytree","weight":42,"lat":35.7101,"lng":139.8107,"category":"tourism"},
    {"name":"Tsukiji Area","weight":38,"lat":35.6654,"lng":139.7707,"category":"commercial"},
    {"name":"Nishi-Nippori Station","weight":25,"lat":35.7320,"lng":139.7670,"category":"local"},
    {"name":"Hikarigaoka Station","weight":22,"lat":35.7617,"lng":139.6378,"category":"local"}
  ]
}
